{
  "project_info": {
    "project_number": "361884763011",
    "firebase_url": "https://citizenandpolice-83361.firebaseio.com",
    "project_id": "citizenandpolice-83361",
    "storage_bucket": "citizenandpolice-83361.appspot.com"
  },
  "client": [
    {
      "client_info": {
        "mobilesdk_app_id": "1:361884763011:android:d6c203649b9e02a319ecb6",
        "android_client_info": {
          "package_name": "com.youssefdirani.citizen"
        }
      },
      "oauth_client": [
        {
          "client_id": "361884763011-retflh3mbvqk9uib0ji9d34392gi1g87.apps.googleusercontent.com",
          "client_type": 3
        }
      ],
      "api_key": [
        {
          "current_key": "AIzaSyD2nskrDn3-SP3FAiQEr6WvDEsAqz9LaoU"
        }
      ],
      "services": {
        "appinvite_service": {
          "other_platform_oauth_client": [
            {
              "client_id": "361884763011-retflh3mbvqk9uib0ji9d34392gi1g87.apps.googleusercontent.com",
              "client_type": 3
            }
          ]
        }
      }
    },
    {
      "client_info": {
        "mobilesdk_app_id": "1:361884763011:android:6e4cc96684b7577319ecb6",
        "android_client_info": {
          "package_name": "com.youssefdirani.police1"
        }
      },
      "oauth_client": [
        {
          "client_id": "361884763011-retflh3mbvqk9uib0ji9d34392gi1g87.apps.googleusercontent.com",
          "client_type": 3
        }
      ],
      "api_key": [
        {
          "current_key": "AIzaSyD2nskrDn3-SP3FAiQEr6WvDEsAqz9LaoU"
        }
      ],
      "services": {
        "appinvite_service": {
          "other_platform_oauth_client": [
            {
              "client_id": "361884763011-retflh3mbvqk9uib0ji9d34392gi1g87.apps.googleusercontent.com",
              "client_type": 3
            }
          ]
        }
      }
    }
  ],
  "configuration_version": "1"
}